imagekit2/__init__.py
imagekit2/__init__.pyi
imagekit2/imagekit2.pypy310-pp73-aarch64-linux-gnu.so
imagekit2/py.typed
imagekit2-0.1.5.dist-info/METADATA
imagekit2-0.1.5.dist-info/WHEEL
imagekit2.pyi
imagekit2-0.1.5.dist-info/RECORD
