Metadata-Version: 2.4
Name: imagekit2
Version: 0.1.5
Classifier: Programming Language :: Rust
Classifier: Programming Language :: Python :: Implementation :: CPython
Classifier: Programming Language :: Python :: Implementation :: PyPy
Summary: A high-performance, Rust-powered image watermarking library. Supports text and logo watermarks, smart contrast, tiling, rotation, and precise positioning.
License: MIT
Requires-Python: >=3.7
